CHANGES.txt
LICENSE.txt
README.txt
setup.py
Products/__init__.py
Products.PloneGetPaid.egg-info/PKG-INFO
Products.PloneGetPaid.egg-info/SOURCES.txt
Products.PloneGetPaid.egg-info/dependency_links.txt
Products.PloneGetPaid.egg-info/entry_points.txt
Products.PloneGetPaid.egg-info/namespace_packages.txt
Products.PloneGetPaid.egg-info/not-zip-safe
Products.PloneGetPaid.egg-info/requires.txt
Products.PloneGetPaid.egg-info/top_level.txt
Products/PloneGetPaid/__init__.py
Products/PloneGetPaid/_patch.py
Products/PloneGetPaid/addressbook.py
Products/PloneGetPaid/cart.py
Products/PloneGetPaid/catalog.py
Products/PloneGetPaid/config.py
Products/PloneGetPaid/configure.zcml
Products/PloneGetPaid/content.py
Products/PloneGetPaid/currencyformatter.py
Products/PloneGetPaid/db-version.txt
Products/PloneGetPaid/events.py
Products/PloneGetPaid/i18n.py
Products/PloneGetPaid/i18n.sh
Products/PloneGetPaid/interfaces.py
Products/PloneGetPaid/intid.zcml
Products/PloneGetPaid/member.py
Products/PloneGetPaid/namedorder.py
Products/PloneGetPaid/notifications.py
Products/PloneGetPaid/overrides.zcml
Products/PloneGetPaid/payment.py
Products/PloneGetPaid/permissions.py
Products/PloneGetPaid/permissions.zcml
Products/PloneGetPaid/plugins.zcml
Products/PloneGetPaid/preferences.py
Products/PloneGetPaid/profiles.zcml
Products/PloneGetPaid/readme.txt
Products/PloneGetPaid/refresh.txt
Products/PloneGetPaid/sessions.py
Products/PloneGetPaid/setuphandlers.py
Products/PloneGetPaid/vocabularies.py
Products/PloneGetPaid/vocabularies.zcml
Products/PloneGetPaid/Extensions/__init__.py
Products/PloneGetPaid/Extensions/gen_order.py
Products/PloneGetPaid/Extensions/install.py
Products/PloneGetPaid/Extensions/plugin.py
Products/PloneGetPaid/Extensions/update_r748_order_id.py
Products/PloneGetPaid/browser/__init__.py
Products/PloneGetPaid/browser/admin.py
Products/PloneGetPaid/browser/admin.zcml
Products/PloneGetPaid/browser/admin_order.py
Products/PloneGetPaid/browser/base.py
Products/PloneGetPaid/browser/cart.py
Products/PloneGetPaid/browser/cart.zcml
Products/PloneGetPaid/browser/checkout.py
Products/PloneGetPaid/browser/configure.zcml
Products/PloneGetPaid/browser/content.py
Products/PloneGetPaid/browser/content.zcml
Products/PloneGetPaid/browser/exception.py
Products/PloneGetPaid/browser/interfaces.py
Products/PloneGetPaid/browser/io.py
