Metadata-Version: 1.1
Name: Products.PloneGetPaid
Version: 0.10.5
Summary: E-commerce framework for Plone
Home-page: http://www.plonegetpaid.com/
Author: GetPaid Team
Author-email: getpaid-dev@googlegroups.com
License: ZPL
Keywords: commerce donation zope plone getpaid
Platform: UNKNOWN
Classifier: Framework :: Plone
Classifier: Programming Language :: Python
Classifier: Framework :: Zope3
Classifier: Intended Audience :: Developers
Classifier: License :: OSI Approved :: Zope Public License
Classifier: Operating System :: OS Independent
Classifier: Topic :: Office/Business :: Financial
Classifier: Topic :: Software Development :: Libraries
